yadapy
