Metadata-Version: 1.0
Name: yadapy
Version: 0.1.0.2
Summary: A framework for building distributed social networking applications and mobile-centric single sign-on.
Home-page: http://www.yadaproject.com/
Author: Matthew Reynold Vogel
Author-email: matt@yadaproject.com
License: UNKNOWN
Download-URL: https://github.com/pdxwebdev/yadapy/zipball/master
Platform: UNKNOWN
Classifier: Environment :: Web Environment
Classifier: Intended Audience :: Developers
Classifier: Operating System :: OS Independent
Classifier: Programming Language :: Python
Classifier: Programming Language :: Python :: 2.6
Classifier: Programming Language :: Python :: 2.7
Classifier: Topic :: Internet :: WWW/HTTP
Classifier: Topic :: Internet :: WWW/HTTP :: Dynamic Content
Classifier: Topic :: Internet :: WWW/HTTP :: WSGI
Classifier: Topic :: Software Development :: Libraries :: Application Frameworks
Classifier: Topic :: Software Development :: Libraries :: Python Modules
